opax/__init__.py
opax/optimizer.py
opax/schedule.py
opax/transform.py
opax/utils.py
opax-0.2.11.dist-info/LICENSE
opax-0.2.11.dist-info/METADATA
opax-0.2.11.dist-info/WHEEL
opax-0.2.11.dist-info/top_level.txt
opax-0.2.11.dist-info/RECORD
